cornojob_killer/__init__.py
cornojob_killer/cli.py
cornojob_killer-0.0.5.dist-info/METADATA
cornojob_killer-0.0.5.dist-info/WHEEL
cornojob_killer-0.0.5.dist-info/entry_points.txt
cornojob_killer-0.0.5.dist-info/top_level.txt
cornojob_killer-0.0.5.dist-info/RECORD
