Metadata-Version: 2.1
Name: cornojob-killer
Version: 0.0.5
Summary: No more cornojobs
Home-page: https://github.com/abstra-app/cornojob-killer
License: MIT
Platform: UNKNOWN
Requires-Dist: abstra
Requires-Dist: requests
